air_labs_bulk_pause_unpause_ui/__init__.py
air_labs_bulk_pause_unpause_ui/air_labs_bulk_pause_unpause_ui.py
air_labs_bulk_pause_unpause_ui/static/index.html
air_labs_bulk_pause_unpause_ui/static/pause-app.js
air_labs_bulk_pause_unpause_ui-0.1.9.dist-info/METADATA
air_labs_bulk_pause_unpause_ui-0.1.9.dist-info/WHEEL
air_labs_bulk_pause_unpause_ui-0.1.9.dist-info/entry_points.txt
air_labs_bulk_pause_unpause_ui-0.1.9.dist-info/RECORD
