Metadata-Version: 2.4
Name: air-labs-bulk-pause-unpause-ui
Version: 0.1.9
Summary: Airflow UI plugin to bulk pause/unpause DAGs.
Author: Rahul Rajasekharan
License: MIT
Requires-Python: >=3.11
Requires-Dist: fastapi>=0.115
